CHANGELOG.txt
LICENSE.txt
MANIFEST.in
README.txt
main.py
setup.py
API/main.py
check_url.egg-info/SOURCES.txt
check_url.egg-info/dependency_links.txt
check_url.egg-info/top_level.txt
checkurl.egg-info/SOURCES.txt
checkurl.egg-info/dependency_links.txt
checkurl.egg-info/top_level.txt
src/__init__.py
src/check_url.py
src/url_is_reacheable.py
unittest/test_package_publication.py
unittest/unit_test.py
urlsStatus.egg-info/SOURCES.txt
urlsStatus.egg-info/dependency_links.txt
urlsStatus.egg-info/top_level.txt
venv/Lib/site-packages/_virtualenv.py
venv/Lib/site-packages/six.py
venv/Lib/site-packages/typing_extensions.py
venv/Lib/site-packages/zipp.py
venv/Lib/site-packages/PyYAML-6.0.dist-info/top_level.txt
venv/Lib/site-packages/Pygments-2.10.0.dist-info/entry_points.txt
venv/Lib/site-packages/Pygments-2.10.0.dist-info/top_level.txt
venv/Lib/site-packages/_distutils_hack/__init__.py
venv/Lib/site-packages/_distutils_hack/override.py
venv/Lib/site-packages/_yaml/__init__.py
venv/Lib/site-packages/anyio/__init__.py
venv/Lib/site-packages/anyio/from_thread.py
venv/Lib/site-packages/anyio/lowlevel.py
venv/Lib/site-packages/anyio/pytest_plugin.py
venv/Lib/site-packages/anyio/to_process.py
venv/Lib/site-packages/anyio/to_thread.py
venv/Lib/site-packages/anyio-3.3.4.dist-info/entry_points.txt
venv/Lib/site-packages/anyio-3.3.4.dist-info/top_level.txt
venv/Lib/site-packages/anyio/_backends/__init__.py
venv/Lib/site-packages/anyio/_backends/_asyncio.py
venv/Lib/site-packages/anyio/_backends/_trio.py
venv/Lib/site-packages/anyio/_core/__init__.py
venv/Lib/site-packages/anyio/_core/_compat.py
venv/Lib/site-packages/anyio/_core/_eventloop.py
venv/Lib/site-packages/anyio/_core/_exceptions.py
venv/Lib/site-packages/anyio/_core/_fileio.py
venv/Lib/site-packages/anyio/_core/_resources.py
venv/Lib/site-packages/anyio/_core/_signals.py
venv/Lib/site-packages/anyio/_core/_sockets.py
venv/Lib/site-packages/anyio/_core/_streams.py
venv/Lib/site-packages/anyio/_core/_subprocesses.py
venv/Lib/site-packages/anyio/_core/_synchronization.py
venv/Lib/site-packages/anyio/_core/_tasks.py
venv/Lib/site-packages/anyio/_core/_testing.py
venv/Lib/site-packages/anyio/_core/_typedattr.py
venv/Lib/site-packages/anyio/abc/__init__.py
venv/Lib/site-packages/anyio/abc/_resources.py
venv/Lib/site-packages/anyio/abc/_sockets.py
venv/Lib/site-packages/anyio/abc/_streams.py
venv/Lib/site-packages/anyio/abc/_subprocesses.py
venv/Lib/site-packages/anyio/abc/_tasks.py
venv/Lib/site-packages/anyio/abc/_testing.py
venv/Lib/site-packages/anyio/streams/__init__.py
venv/Lib/site-packages/anyio/streams/buffered.py
venv/Lib/site-packages/asgiref-3.4.1.dist-info/top_level.txt
venv/Lib/site-packages/bleach-4.1.0.dist-info/top_level.txt
venv/Lib/site-packages/bleach/_vendor/html5lib-1.1.dist-info/top_level.txt
venv/Lib/site-packages/certifi-2021.10.8.dist-info/top_level.txt
venv/Lib/site-packages/charset_normalizer-2.0.7.dist-info/entry_points.txt
venv/Lib/site-packages/charset_normalizer-2.0.7.dist-info/top_level.txt
venv/Lib/site-packages/checkurl-0.0.1.dist-info/LICENSE.txt
venv/Lib/site-packages/checkurl-0.0.1.dist-info/top_level.txt
venv/Lib/site-packages/click-8.0.3.dist-info/top_level.txt
venv/Lib/site-packages/colorama-0.4.4.dist-info/LICENSE.txt
venv/Lib/site-packages/colorama-0.4.4.dist-info/top_level.txt
venv/Lib/site-packages/docutils-0.18.dist-info/COPYING.txt
venv/Lib/site-packages/docutils-0.18.dist-info/top_level.txt
venv/Lib/site-packages/h11-0.12.0.dist-info/LICENSE.txt
venv/Lib/site-packages/h11-0.12.0.dist-info/top_level.txt
venv/Lib/site-packages/httptools-0.2.0.dist-info/top_level.txt
venv/Lib/site-packages/idna-3.3.dist-info/top_level.txt
venv/Lib/site-packages/importlib_metadata-4.8.2.dist-info/top_level.txt
venv/Lib/site-packages/keyring-23.2.1.dist-info/entry_points.txt
venv/Lib/site-packages/keyring-23.2.1.dist-info/top_level.txt
venv/Lib/site-packages/packaging-21.3.dist-info/top_level.txt
venv/Lib/site-packages/pip-21.1.2.dist-info/LICENSE.txt
venv/Lib/site-packages/pip-21.1.2.dist-info/entry_points.txt
venv/Lib/site-packages/pip-21.1.2.dist-info/top_level.txt
venv/Lib/site-packages/pkginfo-1.8.0.dist-info/LICENSE.txt
venv/Lib/site-packages/pkginfo-1.8.0.dist-info/entry_points.txt
venv/Lib/site-packages/pkginfo-1.8.0.dist-info/top_level.txt
venv/Lib/site-packages/pydantic-1.8.2.dist-info/entry_points.txt
venv/Lib/site-packages/pydantic-1.8.2.dist-info/top_level.txt
venv/Lib/site-packages/pyparsing-3.0.6.dist-info/top_level.txt
venv/Lib/site-packages/python_dotenv-0.19.2.dist-info/entry_points.txt
venv/Lib/site-packages/python_dotenv-0.19.2.dist-info/top_level.txt
venv/Lib/site-packages/pywin32_ctypes-0.2.0.dist-info/LICENSE.txt
venv/Lib/site-packages/pywin32_ctypes-0.2.0.dist-info/top_level.txt
venv/Lib/site-packages/readme_renderer-30.0.dist-info/entry_points.txt
venv/Lib/site-packages/readme_renderer-30.0.dist-info/top_level.txt
venv/Lib/site-packages/requests-2.26.0.dist-info/top_level.txt
venv/Lib/site-packages/requests_toolbelt-0.9.1.dist-info/top_level.txt
venv/Lib/site-packages/rfc3986-1.5.0.dist-info/top_level.txt
venv/Lib/site-packages/setuptools-57.0.0.dist-info/dependency_links.txt
venv/Lib/site-packages/setuptools-57.0.0.dist-info/entry_points.txt
venv/Lib/site-packages/setuptools-57.0.0.dist-info/top_level.txt
venv/Lib/site-packages/six-1.16.0.dist-info/top_level.txt
venv/Lib/site-packages/sniffio-1.2.0.dist-info/top_level.txt
venv/Lib/site-packages/starlette-0.16.0.dist-info/top_level.txt
venv/Lib/site-packages/tqdm-4.62.3.dist-info/entry_points.txt
venv/Lib/site-packages/tqdm-4.62.3.dist-info/top_level.txt
venv/Lib/site-packages/twine-3.6.0.dist-info/entry_points.txt
venv/Lib/site-packages/twine-3.6.0.dist-info/top_level.txt
venv/Lib/site-packages/urllib3-1.26.7.dist-info/LICENSE.txt
venv/Lib/site-packages/urllib3-1.26.7.dist-info/top_level.txt
venv/Lib/site-packages/urlsStatus-0.0.2.dist-info/LICENSE.txt
venv/Lib/site-packages/urlsStatus-0.0.2.dist-info/top_level.txt
