Metadata-Version: 2.1
Name: verified-url
Version: 0.0.3
Summary: Package for check url
Home-page: UNKNOWN
Author: Maxime JARRY
Author-email: maxime.jarry@outlook.com
License: MIT
Keywords: URL,STATUS
Platform: UNKNOWN
Classifier: Development Status :: 5 - Production/Stable
Classifier: Intended Audience :: Developers
Classifier: Operating System :: Microsoft
Classifier: Operating System :: Unix
Classifier: Operating System :: MacOS
Classifier: License :: OSI Approved :: MIT License
Classifier: Programming Language :: Python :: 3
License-File: LICENSE.txt
